pyemenu/__init__.py
pyemenu/colors.py
pyemenu/tools.py
pyemenu/components/__init__.py
pyemenu/components/buttons.py
pyemenu/components/checkboxs.py
pyemenu/components/entries.py
pyemenu/components/texts.py
pyemenu/components/titles.py
pyemenu/widgets/__init__.py
pyemenu/widgets/checkboxlists.py
pyemenu/widgets/forms.py
pyemenu/widgets/menus.py
pyemenu-1.0.1.dist-info/LICENSE.txt
pyemenu-1.0.1.dist-info/METADATA
pyemenu-1.0.1.dist-info/WHEEL
pyemenu-1.0.1.dist-info/top_level.txt
pyemenu-1.0.1.dist-info/RECORD
