Metadata-Version: 2.1
Name: pyemenu
Version: 1.0.1
Summary: Easy and Simple kit for develop Text User Interfaces
Home-page: https://github.com/FreireAlexander/PyeMenu
Download-URL: https://github.com/FreireAlexander/PyeMenu/releases/tag/1.0.1
Author: Freire Alexander Palomino Palma
Author-email: freirealexander0214@gmail.com
License: MIT
Project-URL: Bug Tracker, https://github.com/FreireAlexander/PyeMenu/issues
Keywords: MENU,CLI,command line,TUI,Text User Interface
Classifier: Development Status :: 3 - Alpha
Classifier: Intended Audience :: Developers
Classifier: Topic :: Software Development :: Build Tools
Classifier: License :: OSI Approved :: MIT License
Classifier: Programming Language :: Python :: 3.7
Classifier: Programming Language :: Python :: 3.8
Classifier: Programming Language :: Python :: 3.9
Classifier: Programming Language :: Python :: 3.10
Classifier: Programming Language :: Python :: 3.11
Requires-Python: >=3.7
License-File: LICENSE.txt
